honu/__init__.py
honu/__main__.py
honu/cli.py
honu/display.py
honu/functions.py
honu/game.py
honu/graphics.py
honu/honu.py
honu/sprites.py
honu/test_cases.py
honu/testcases.py
honu/cli/__init__.py
honu/cli/honu_doc.py
honu/cli/honu_test.py
honu/static/__init__.py
honu/static/levels/0.json
honu/static/levels/__init__.py
honu/static/sprites/__init__.py
honu/static/sprites/flag.png
honu/static/sprites/turtle.png
Honu-0.0.2.dist-info/LICENCE.rst
Honu-0.0.2.dist-info/METADATA
Honu-0.0.2.dist-info/WHEEL
Honu-0.0.2.dist-info/entry_points.txt
Honu-0.0.2.dist-info/top_level.txt
Honu-0.0.2.dist-info/RECORD
